asprise_ocr_api/aocr.xsl
asprise_ocr_api/icon.ico
asprise_ocr_api/ocr.py
asprise_ocr_api/ocr_app.py
asprise_ocr_api/__init__.py
asprise_ocr_sdk_python_api-15.3.0.8.dist-info/DESCRIPTION.rst
asprise_ocr_sdk_python_api-15.3.0.8.dist-info/entry_points.txt
asprise_ocr_sdk_python_api-15.3.0.8.dist-info/METADATA
asprise_ocr_sdk_python_api-15.3.0.8.dist-info/metadata.json
asprise_ocr_sdk_python_api-15.3.0.8.dist-info/RECORD
asprise_ocr_sdk_python_api-15.3.0.8.dist-info/top_level.txt
asprise_ocr_sdk_python_api-15.3.0.8.dist-info/WHEEL
