Metadata-Version: 2.0
Name: asprise-ocr-sdk-python-api
Version: 15.3.0.8
Summary: Asprise OCR (optical character recognition) and barcode recognition SDK is a high performance royalty-free Python API library. It converts images (JPEG, PNG, TIFF, PDF, etc) into text, xml, searchable PDF or editable RTF/Word formats. Data capture are supported for processing documents like invoices and forms.
Home-page: http://asprise.com/royalty-free-library/python-ocr-sdk-asprise_ocr_api-overview.html
Author: Asprise OCR
Author-email: support@asprise.com
License: ASPRISE OCR SDK LICENSE
Keywords: Asprise OCR SDK Image Convert Text Searchable PDF Barcode Recognition Invoice Form OMR
Platform: UNKNOWN
Classifier: Development Status :: 6 - Mature
Classifier: Environment :: Console
Classifier: Environment :: MacOS X
Classifier: Environment :: Win32 (MS Windows)
Classifier: Environment :: Other Environment
Classifier: Framework :: Django
Classifier: Intended Audience :: Developers
Classifier: Intended Audience :: Financial and Insurance Industry
Classifier: Intended Audience :: Healthcare Industry
Classifier: Intended Audience :: Information Technology
Classifier: Intended Audience :: Science/Research
Classifier: License :: Freely Distributable
Classifier: License :: Other/Proprietary License
Classifier: Natural Language :: English
Classifier: Natural Language :: French
Classifier: Operating System :: MacOS
Classifier: Operating System :: Microsoft
Classifier: Operating System :: POSIX
Classifier: Operating System :: Unix
Classifier: Programming Language :: Java
Classifier: Programming Language :: Python
Classifier: Topic :: Office/Business
Classifier: Topic :: Scientific/Engineering :: Image Recognition
Classifier: Topic :: Scientific/Engineering :: Information Analysis
Classifier: Topic :: Software Development :: Libraries
Classifier: Topic :: Software Development :: Libraries :: Python Modules
Classifier: Topic :: Text Processing :: General
Classifier: Topic :: Utilities
